[
  {
    "id": 1,
    "owner": "Jason",
    "teamName": "Belltown Raptors",
    "record": "7-7-0",
    "fptsFor": 1751,
    "fptsAgainst": 1615,
    "playoffResult": "1st – Champion",
    "eliminatedBy": "-",
    "rankFptsFor": 6,
    "rankFptsAgainst": 9
  },
  {
    "id": 2,
    "owner": "Patrick",
    "teamName": "Belleview Badgers",
    "record": "10-4-0",
    "fptsFor": 1947,
    "fptsAgainst": 1562,
    "playoffResult": "2nd Round Exit – Lost to Belltown Raptors (134.84–103.92)",
    "eliminatedBy": "Belltown Raptors",
    "rankFptsFor": 1,
    "rankFptsAgainst": 4
  },
  {
    "id": 7,
    "owner": "Matthew M",
    "teamName": "Red Pandas",
    "record": "6-8-0",
    "fptsFor": 1622,
    "fptsAgainst": 1608,
    "playoffResult": "Missed Playoffs",
    "eliminatedBy": null,
    "rankFptsFor": 7,
    "rankFptsAgainst": 8
  },
  {
    "id": 4,
    "owner": "Noah / Shane",
    "teamName": "Double Trouble",
    "record": "10-4-0",
    "fptsFor": 1892,
    "fptsAgainst": 1556,
    "playoffResult": "2nd – Finals Loss vs Belltown Raptors (138.76–127.24)",
    "eliminatedBy": "Belltown Raptors",
    "rankFptsFor": 2,
    "rankFptsAgainst": 3
  },
  {
    "id": 3,
    "owner": "Michael M",
    "teamName": "Mt. Lebanon Cake Eaters ",
    "record": "11-3-0",
    "fptsFor": 1773,
    "fptsAgainst": 1579,
    "playoffResult": "1st Round Exit – Lost to Belltown Raptors (149.10–109.40)",
    "eliminatedBy": "Belltown Raptors",
    "rankFptsFor": 4,
    "rankFptsAgainst": 6
  },
  {
    "id": 8,
    "owner": "Joseph",
    "teamName": "Elemental Heroes",
    "record": "11-3-0",
    "fptsFor": 1874,
    "fptsAgainst": 1524,
    "playoffResult": "1st Round Exit – Lost to Detroit Dawgs (200.78–126.42)",
    "eliminatedBy": "Detroit Dawgs",
    "rankFptsFor": 3,
    "rankFptsAgainst": 2
  },
  {
    "id": 9,
    "owner": "Jack",
    "teamName": "bop pop",
    "record": "10-4-0",
    "fptsFor": 1772,
    "fptsAgainst": 1422,
    "playoffResult": "1st Round Exit – Lost to Double Trouble (234.06–109.64)",
    "eliminatedBy": "Double Trouble",
    "rankFptsFor": 5,
    "rankFptsAgainst": 1
  },
  {
    "id": 11,
    "owner": "Alex",
    "teamName": "Bimg Bamg Boomg",
    "record": "0-14-0",
    "fptsFor": 772,
    "fptsAgainst": 1601,
    "playoffResult": "Missed Playoffs",
    "eliminatedBy": null,
    "rankFptsFor": 12,
    "rankFptsAgainst": 7
  },
  {
    "id": 12,
    "owner": "Conor",
    "teamName": "Detroit Dawgs",
    "record": "7-7-0",
    "fptsFor": 1596,
    "fptsAgainst": 1670,
    "playoffResult": "2nd Round Exit – Lost to Double Trouble (172.12–135.92)",
    "eliminatedBy": "Double Trouble",
    "rankFptsFor": 9,
    "rankFptsAgainst": 11
  },
  {
    "id": 5,
    "owner": "Ginger",
    "teamName": "The Lone Ginger",
    "record": "3-11-0",
    "fptsFor": 1388,
    "fptsAgainst": 1692,
    "playoffResult": "Missed Playoffs",
    "eliminatedBy": null,
    "rankFptsFor": 10,
    "rankFptsAgainst": 12
  },
  {
    "id": 6,
    "owner": "Matt S",
    "teamName": "Minshew's Maniacs",
    "record": "1-13-0",
    "fptsFor": 1018,
    "fptsAgainst": 1571,
    "playoffResult": "Missed Playoffs",
    "eliminatedBy": null,
    "rankFptsFor": 11,
    "rankFptsAgainst": 5
  },
  {
    "id": 10,
    "owner": "Michael B",
    "teamName": "BeerNeverBrokeMyHeart",
    "record": "8-6-0",
    "fptsFor": 1610,
    "fptsAgainst": 1617,
    "playoffResult": "1st Round Exit – Lost to Belleview Badgers (129.92–112.38)",
    "eliminatedBy": "Belleview Badgers",
    "rankFptsFor": 8,
    "rankFptsAgainst": 10
  }
]
